weft_client.py
openapi_client/__init__.py
openapi_client/api_client.py
openapi_client/api_response.py
openapi_client/configuration.py
openapi_client/exceptions.py
openapi_client/py.typed
openapi_client/rest.py
openapi_client/schemas.py
openapi_client/api/__init__.py
openapi_client/api/auth_api.py
openapi_client/api/events_api.py
openapi_client/apis/__init__.py
openapi_client/apis/path_to_api.py
openapi_client/apis/tag_to_api.py
openapi_client/apis/paths/__init__.py
openapi_client/apis/paths/events.py
openapi_client/apis/paths/login.py
openapi_client/apis/paths/refresh_token.py
openapi_client/apis/tags/__init__.py
openapi_client/apis/tags/auth_api.py
openapi_client/apis/tags/events_api.py
openapi_client/model/__init__.py
openapi_client/model/event_input.py
openapi_client/model/login_request_schema.py
openapi_client/model/login_response_schema.py
openapi_client/model/refresh_token_input.py
openapi_client/model/refresh_token_response.py
openapi_client/model/send_events_request_schema.py
openapi_client/models/__init__.py
openapi_client/models/event_input.py
openapi_client/models/login_request.py
openapi_client/models/login_response.py
openapi_client/models/send_events_request.py
openapi_client/paths/__init__.py
openapi_client/paths/events/__init__.py
openapi_client/paths/events/post.py
openapi_client/paths/events/put.py
openapi_client/paths/login/__init__.py
openapi_client/paths/login/post.py
openapi_client/paths/refresh_token/__init__.py
openapi_client/paths/refresh_token/post.py
src/__init__.py
src/weft_client.py
src/openapi_client/__init__.py
src/openapi_client/api_client.py
src/openapi_client/api_response.py
src/openapi_client/configuration.py
src/openapi_client/exceptions.py
src/openapi_client/rest.py
src/openapi_client/api/__init__.py
src/openapi_client/api/auth_api.py
src/openapi_client/api/events_api.py
src/openapi_client/models/__init__.py
src/openapi_client/models/event_input.py
src/openapi_client/models/login_request.py
weft_client-1.2.7.dist-info/METADATA
weft_client-1.2.7.dist-info/WHEEL
weft_client-1.2.7.dist-info/top_level.txt
weft_client-1.2.7.dist-info/RECORD
