Metadata-Version: 2.1
Name: weft-client
Version: 1.2.7
Summary: Weft Event Ingestion API
Home-page: 
Author: Weft Finance, Inc
Author-email: team@goweft.com
Keywords: OpenAPI,OpenAPI-Generator,Weft Event Ingestion API
Requires-Python: >=3.7
Requires-Dist: python-dateutil >=2.5.3
Requires-Dist: setuptools >=21.0.0
Requires-Dist: urllib3 <2.1.0,>=1.25.3
Requires-Dist: pydantic <2,>=1.10.5
Requires-Dist: aenum >=3.1.11
